{"flowContents":{"identifier":"174befb0-0196-1000-15f9-7c703e88cf68","instanceIdentifier":"2e41e224-f330-320d-2380-ff9cff2ca200","name":"EcomData_Enhanced","comments":"","position":{"x":600.0,"y":-400.0},"processGroups":[],"remoteProcessGroups":[],"processors":[{"identifier":"174befb7-0196-1000-5804-f2bc08b4b11e","instanceIdentifier":"ff3244f0-3d66-3e11-352c-335a1e91a1cf","name":"Get_All_Files","comments":"","position":{"x":-56.0,"y":-464.0},"type":"org.apache.nifi.processors.standard.GetFile","bundle":{"group":"org.apache.nifi","artifact":"nifi-standard-nar","version":"2.3.0"},"properties":{"Keep Source File":"false","Minimum File Age":"0 sec","Polling Interval":"0 sec","Input Directory":"/staging","Maximum File Age":null,"Batch Size":"10","Maximum File Size":null,"Minimum File Size":"0 B","Ignore Hidden Files":"true","Recurse Subdirectories":"true","File Filter":".*\\.(csv|json)","Path Filter":null},"propertyDescriptors":{"Keep Source File":{"name":"Keep Source File","displayName":"Keep Source File","identifiesControllerService":false,"sensitive":false,"dynamic":false},"Minimum File Age":{"name":"Minimum File Age","displayName":"Minimum File Age","identifiesControllerService":false,"sensitive":false,"dynamic":false},"Polling Interval":{"name":"Polling Interval","displayName":"Polling Interval","identifiesControllerService":false,"sensitive":false,"dynamic":false},"Input Directory":{"name":"Input Directory","displayName":"Input Directory","identifiesControllerService":false,"sensitive":false,"dynamic":false},"Maximum File Age":{"name":"Maximum File Age","displayName":"Maximum File Age","identifiesControllerService":false,"sensitive":false,"dynamic":false},"Batch Size":{"name":"Batch Size","displayName":"Batch Size","identifiesControllerService":false,"sensitive":false,"dynamic":false},"Maximum File Size":{"name":"Maximum File Size","displayName":"Maximum File Size","identifiesControllerService":false,"sensitive":false,"dynamic":false},"Minimum File Size":{"name":"Minimum File Size","displayName":"Minimum File Size","identifiesControllerService":false,"sensitive":false,"dynamic":false},"Ignore Hidden Files":{"name":"Ignore Hidden Files","displayName":"Ignore Hidden Files","identifiesControllerService":false,"sensitive":false,"dynamic":false},"Recurse Subdirectories":{"name":"Recurse Subdirectories","displayName":"Recurse Subdirectories","identifiesControllerService":false,"sensitive":false,"dynamic":false},"File Filter":{"name":"File Filter","displayName":"File Filter","identifiesControllerService":false,"sensitive":false,"dynamic":false},"Path Filter":{"name":"Path Filter","displayName":"Path Filter","identifiesControllerService":false,"sensitive":false,"dynamic":false}},"style":{},"schedulingPeriod":"0 sec","schedulingStrategy":"TIMER_DRIVEN","executionNode":"ALL","penaltyDuration":"30 sec","yieldDuration":"1 sec","bulletinLevel":"WARN","runDurationMillis":0,"concurrentlySchedulableTaskCount":1,"autoTerminatedRelationships":[],"scheduledState":"ENABLED","retryCount":10,"retriedRelationships":[],"backoffMechanism":"PENALIZE_FLOWFILE","maxBackoffPeriod":"10 mins","componentType":"PROCESSOR","groupIdentifier":"174befb0-0196-1000-15f9-7c703e88cf68"},{"identifier":"174befb8-0196-1000-626b-60be34431bf7","instanceIdentifier":"d9755ed1-bb6c-397a-33bc-7c03e3b5cfde","name":"Send_to_Minio","comments":"","position":{"x":-312.0,"y":168.0},"type":"org.apache.nifi.processors.aws.s3.PutS3Object","bundle":{"group":"org.apache.nifi","artifact":"nifi-aws-nar","version":"2.3.0"},"properties":{"FullControl User List":"${s3.permissions.full.users}","Owner":"${s3.owner}","proxy-configuration-service":null,"Resource Transfer Source":"FLOWFILE_CONTENT","Cache Control":null,"s3-object-remove-tags-prefix":"false","Endpoint Override URL":"http://minio:9000","File Resource Service":null,"Multipart Upload Max Age Threshold":"7 days","custom-signer-class-name":null,"canned-acl":"${s3.permissions.cannedacl}","custom-signer-module-location":null,"Signer Override":"Default Signature","Content Type":null,"server-side-encryption":"None","Write ACL User List":"${s3.permissions.writeacl.users}","encryption-service":null,"Read ACL User List":"${s3.permissions.readacl.users}","Content Disposition":null,"Storage Class":"Standard","Multipart Part Size":"5 GB","use-chunked-encoding":"true","Object Key":"${filename}","AWS Credentials Provider service":"174befb2-0196-1000-7005-86a08a1862c1","Multipart Threshold":"5 GB","s3-object-tags-prefix":null,"SSL Context Service":null,"Bucket":"test","Multipart Upload AgeOff Interval":"60 min","use-path-style-access":"false","Write Permission User List":"${s3.permissions.write.users}","Communications Timeout":"30 secs","Region":"us-west-2","Read Permission User List":"${s3.permissions.read.users}","Expiration Time Rule":null,"s3-temporary-directory-multipart":"${java.io.tmpdir}"},"propertyDescriptors":{"FullControl User List":{"name":"FullControl User List","displayName":"FullControl User List","identifiesControllerService":false,"sensitive":false,"dynamic":false},"Owner":{"name":"Owner","displayName":"Owner","identifiesControllerService":false,"sensitive":false,"dynamic":false},"proxy-configuration-service":{"name":"proxy-configuration-service","displayName":"Proxy Configuration Service","identifiesControllerService":true,"sensitive":false,"dynamic":false},"Resource Transfer Source":{"name":"Resource Transfer Source","displayName":"Resource Transfer Source","identifiesControllerService":false,"sensitive":false,"dynamic":false},"Cache Control":{"name":"Cache Control","displayName":"Cache Control","identifiesControllerService":false,"sensitive":false,"dynamic":false},"s3-object-remove-tags-prefix":{"name":"s3-object-remove-tags-prefix","displayName":"Remove Tag Prefix","identifiesControllerService":false,"sensitive":false,"dynamic":false},"Endpoint Override URL":{"name":"Endpoint Override URL","displayName":"Endpoint Override URL","identifiesControllerService":false,"sensitive":false,"dynamic":false},"File Resource Service":{"name":"File Resource Service","displayName":"File Resource Service","identifiesControllerService":true,"sensitive":false,"dynamic":false},"Multipart Upload Max Age Threshold":{"name":"Multipart Upload Max Age Threshold","displayName":"Multipart Upload Max Age Threshold","identifiesControllerService":false,"sensitive":false,"dynamic":false},"custom-signer-class-name":{"name":"custom-signer-class-name","displayName":"Custom Signer Class Name","identifiesControllerService":false,"sensitive":false,"dynamic":false},"canned-acl":{"name":"canned-acl","displayName":"Canned ACL","identifiesControllerService":false,"sensitive":false,"dynamic":false},"custom-signer-module-location":{"name":"custom-signer-module-location","displayName":"Custom Signer Module Location","identifiesControllerService":false,"sensitive":false,"dynamic":false,"resourceDefinition":{"cardinality":"MULTIPLE","resourceTypes":["FILE","DIRECTORY"]}},"Signer Override":{"name":"Signer Override","displayName":"Signer Override","identifiesControllerService":false,"sensitive":false,"dynamic":false},"Content Type":{"name":"Content Type","displayName":"Content Type","identifiesControllerService":false,"sensitive":false,"dynamic":false},"server-side-encryption":{"name":"server-side-encryption","displayName":"Server Side Encryption","identifiesControllerService":false,"sensitive":false,"dynamic":false},"Write ACL User List":{"name":"Write ACL User List","displayName":"Write ACL User List","identifiesControllerService":false,"sensitive":false,"dynamic":false},"encryption-service":{"name":"encryption-service","displayName":"Encryption Service","identifiesControllerService":true,"sensitive":false,"dynamic":false},"Read ACL User List":{"name":"Read ACL User List","displayName":"Read ACL User List","identifiesControllerService":false,"sensitive":false,"dynamic":false},"Content Disposition":{"name":"Content Disposition","displayName":"Content Disposition","identifiesControllerService":false,"sensitive":false,"dynamic":false},"Storage Class":{"name":"Storage Class","displayName":"Storage Class","identifiesControllerService":false,"sensitive":false,"dynamic":false},"Multipart Part Size":{"name":"Multipart Part Size","displayName":"Multipart Part Size","identifiesControllerService":false,"sensitive":false,"dynamic":false},"use-chunked-encoding":{"name":"use-chunked-encoding","displayName":"Use Chunked Encoding","identifiesControllerService":false,"sensitive":false,"dynamic":false},"Object Key":{"name":"Object Key","displayName":"Object Key","identifiesControllerService":false,"sensitive":false,"dynamic":false},"AWS Credentials Provider service":{"name":"AWS Credentials Provider service","displayName":"AWS Credentials Provider Service","identifiesControllerService":true,"sensitive":false,"dynamic":false},"Multipart Threshold":{"name":"Multipart Threshold","displayName":"Multipart Threshold","identifiesControllerService":false,"sensitive":false,"dynamic":false},"s3-object-tags-prefix":{"name":"s3-object-tags-prefix","displayName":"Object Tags Prefix","identifiesControllerService":false,"sensitive":false,"dynamic":false},"SSL Context Service":{"name":"SSL Context Service","displayName":"SSL Context Service","identifiesControllerService":true,"sensitive":false,"dynamic":false},"Bucket":{"name":"Bucket","displayName":"Bucket","identifiesControllerService":false,"sensitive":false,"dynamic":false},"Multipart Upload AgeOff Interval":{"name":"Multipart Upload AgeOff Interval","displayName":"Multipart Upload AgeOff Interval","identifiesControllerService":false,"sensitive":false,"dynamic":false},"use-path-style-access":{"name":"use-path-style-access","displayName":"Use Path Style Access","identifiesControllerService":false,"sensitive":false,"dynamic":false},"Write Permission User List":{"name":"Write Permission User List","displayName":"Write Permission User List","identifiesControllerService":false,"sensitive":false,"dynamic":false},"Communications Timeout":{"name":"Communications Timeout","displayName":"Communications Timeout","identifiesControllerService":false,"sensitive":false,"dynamic":false},"Region":{"name":"Region","displayName":"Region","identifiesControllerService":false,"sensitive":false,"dynamic":false},"Read Permission User List":{"name":"Read Permission User List","displayName":"Read Permission User List","identifiesControllerService":false,"sensitive":false,"dynamic":false},"Expiration Time Rule":{"name":"Expiration Time Rule","displayName":"Expiration Time Rule","identifiesControllerService":false,"sensitive":false,"dynamic":false},"s3-temporary-directory-multipart":{"name":"s3-temporary-directory-multipart","displayName":"Temporary Directory Multipart State","identifiesControllerService":false,"sensitive":false,"dynamic":false}},"style":{},"schedulingPeriod":"0 sec","schedulingStrategy":"TIMER_DRIVEN","executionNode":"ALL","penaltyDuration":"30 sec","yieldDuration":"1 sec","bulletinLevel":"WARN","runDurationMillis":0,"concurrentlySchedulableTaskCount":1,"autoTerminatedRelationships":[],"scheduledState":"ENABLED","retryCount":10,"retriedRelationships":[],"backoffMechanism":"PENALIZE_FLOWFILE","maxBackoffPeriod":"10 mins","componentType":"PROCESSOR","groupIdentifier":"174befb0-0196-1000-15f9-7c703e88cf68"},{"identifier":"58fdcc64-3941-3d50-942c-29abd9243e63","instanceIdentifier":"177671cd-0196-1000-d80c-11354b033e8c","name":"Validate_Files","comments":"","position":{"x":-56.0,"y":-264.0},"type":"org.apache.nifi.processors.standard.RouteOnAttribute","bundle":{"group":"org.apache.nifi","artifact":"nifi-standard-nar","version":"2.3.0"},"properties":{"valid":"${fileSize:gt(0)}","Routing Strategy":"Route to Property name"},"propertyDescriptors":{"valid":{"name":"valid","displayName":"valid","identifiesControllerService":false,"sensitive":false,"dynamic":true},"Routing Strategy":{"name":"Routing Strategy","displayName":"Routing Strategy","identifiesControllerService":false,"sensitive":false,"dynamic":false}},"style":{},"schedulingPeriod":"0 sec","schedulingStrategy":"TIMER_DRIVEN","executionNode":"ALL","penaltyDuration":"30 sec","yieldDuration":"1 sec","bulletinLevel":"WARN","runDurationMillis":25,"concurrentlySchedulableTaskCount":1,"autoTerminatedRelationships":[],"scheduledState":"ENABLED","retryCount":10,"retriedRelationships":[],"backoffMechanism":"PENALIZE_FLOWFILE","maxBackoffPeriod":"10 mins","componentType":"PROCESSOR","groupIdentifier":"174befb0-0196-1000-15f9-7c703e88cf68"},{"identifier":"64a0f0f6-1840-32d3-8e66-09b9409e7fd6","instanceIdentifier":"1752cce6-0196-1000-e2fd-e74824f2892b","name":"Log_CSV_Error","comments":"","position":{"x":-672.0,"y":384.0},"type":"org.apache.nifi.processors.standard.LogAttribute","bundle":{"group":"org.apache.nifi","artifact":"nifi-standard-nar","version":"2.3.0"},"properties":{"Log prefix":null,"character-set":"UTF-8","Log FlowFile Properties":"true","Log Level":"error","attributes-to-ignore-regex":null,"Attributes to Ignore":null,"Attributes to Log":"filename, s3.error","attributes-to-log-regex":".*","Output Format":"Line per Attribute","Log Payload":"false"},"propertyDescriptors":{"Log prefix":{"name":"Log prefix","displayName":"Log prefix","identifiesControllerService":false,"sensitive":false,"dynamic":false},"character-set":{"name":"character-set","displayName":"Character Set","identifiesControllerService":false,"sensitive":false,"dynamic":false},"Log FlowFile Properties":{"name":"Log FlowFile Properties","displayName":"Log FlowFile Properties","identifiesControllerService":false,"sensitive":false,"dynamic":false},"Log Level":{"name":"Log Level","displayName":"Log Level","identifiesControllerService":false,"sensitive":false,"dynamic":false},"attributes-to-ignore-regex":{"name":"attributes-to-ignore-regex","displayName":"Attributes to Ignore by Regular Expression","identifiesControllerService":false,"sensitive":false,"dynamic":false},"Attributes to Ignore":{"name":"Attributes to Ignore","displayName":"Attributes to Ignore","identifiesControllerService":false,"sensitive":false,"dynamic":false},"Attributes to Log":{"name":"Attributes to Log","displayName":"Attributes to Log","identifiesControllerService":false,"sensitive":false,"dynamic":false},"attributes-to-log-regex":{"name":"attributes-to-log-regex","displayName":"Attributes to Log by Regular Expression","identifiesControllerService":false,"sensitive":false,"dynamic":false},"Output Format":{"name":"Output Format","displayName":"Output Format","identifiesControllerService":false,"sensitive":false,"dynamic":false},"Log Payload":{"name":"Log Payload","displayName":"Log Payload","identifiesControllerService":false,"sensitive":false,"dynamic":false}},"style":{},"schedulingPeriod":"0 sec","schedulingStrategy":"TIMER_DRIVEN","executionNode":"ALL","penaltyDuration":"30 sec","yieldDuration":"1 sec","bulletinLevel":"WARN","runDurationMillis":25,"concurrentlySchedulableTaskCount":1,"autoTerminatedRelationships":["success"],"scheduledState":"ENABLED","retryCount":10,"retriedRelationships":[],"backoffMechanism":"PENALIZE_FLOWFILE","maxBackoffPeriod":"10 mins","componentType":"PROCESSOR","groupIdentifier":"174befb0-0196-1000-15f9-7c703e88cf68"},{"identifier":"174befb6-0196-1000-3f9b-6fd2ea757cb1","instanceIdentifier":"32ee6041-6780-3c00-59ba-2ecbbe4f32c1","name":"PublishKafka","comments":"","position":{"x":272.0,"y":160.0},"type":"org.apache.nifi.kafka.processors.PublishKafka","bundle":{"group":"org.apache.nifi","artifact":"nifi-kafka-nar","version":"2.3.0"},"properties":{"compression.type":"none","acks":"all","Message Demarcator":null,"Kafka Key Attribute Encoding":"utf-8","Record Reader":"174befb1-0196-1000-2b5d-6c0654ef430b","Record Metadata Strategy":"FROM_PROPERTIES","Transactional ID Prefix":null,"Header Encoding":"UTF-8","max.request.size":"1 MB","Topic Name":"test","Kafka Key":null,"partition":null,"Kafka Connection Service":"174befb4-0196-1000-0bc1-7163d0c50f3f","Publish Strategy":"USE_VALUE","Record Key Writer":null,"Failure Strategy":"Route to Failure","partitioner.class":"org.apache.kafka.clients.producer.internals.DefaultPartitioner","Record Writer":"174befb3-0196-1000-d024-21e680a6371c","Transactions Enabled":"false","Message Key Field":null,"FlowFile Attribute Header Pattern":null},"propertyDescriptors":{"compression.type":{"name":"compression.type","displayName":"Compression Type","identifiesControllerService":false,"sensitive":false,"dynamic":false},"acks":{"name":"acks","displayName":"Delivery Guarantee","identifiesControllerService":false,"sensitive":false,"dynamic":false},"Message Demarcator":{"name":"Message Demarcator","displayName":"Message Demarcator","identifiesControllerService":false,"sensitive":false,"dynamic":false},"Kafka Key Attribute Encoding":{"name":"Kafka Key Attribute Encoding","displayName":"Kafka Key Attribute Encoding","identifiesControllerService":false,"sensitive":false,"dynamic":false},"Record Reader":{"name":"Record Reader","displayName":"Record Reader","identifiesControllerService":true,"sensitive":false,"dynamic":false},"Record Metadata Strategy":{"name":"Record Metadata Strategy","displayName":"Record Metadata Strategy","identifiesControllerService":false,"sensitive":false,"dynamic":false},"Transactional ID Prefix":{"name":"Transactional ID Prefix","displayName":"Transactional ID Prefix","identifiesControllerService":false,"sensitive":false,"dynamic":false},"Header Encoding":{"name":"Header Encoding","displayName":"Header Encoding","identifiesControllerService":false,"sensitive":false,"dynamic":false},"max.request.size":{"name":"max.request.size","displayName":"Max Request Size","identifiesControllerService":false,"sensitive":false,"dynamic":false},"Topic Name":{"name":"Topic Name","displayName":"Topic Name","identifiesControllerService":false,"sensitive":false,"dynamic":false},"Kafka Key":{"name":"Kafka Key","displayName":"Kafka Key","identifiesControllerService":false,"sensitive":false,"dynamic":false},"partition":{"name":"partition","displayName":"Partition","identifiesControllerService":false,"sensitive":false,"dynamic":false},"Kafka Connection Service":{"name":"Kafka Connection Service","displayName":"Kafka Connection Service","identifiesControllerService":true,"sensitive":false,"dynamic":false},"Publish Strategy":{"name":"Publish Strategy","displayName":"Publish Strategy","identifiesControllerService":false,"sensitive":false,"dynamic":false},"Record Key Writer":{"name":"Record Key Writer","displayName":"Record Key Writer","identifiesControllerService":true,"sensitive":false,"dynamic":false},"Failure Strategy":{"name":"Failure Strategy","displayName":"Failure Strategy","identifiesControllerService":false,"sensitive":false,"dynamic":false},"partitioner.class":{"name":"partitioner.class","displayName":"Partitioner Class","identifiesControllerService":false,"sensitive":false,"dynamic":false},"Record Writer":{"name":"Record Writer","displayName":"Record Writer","identifiesControllerService":true,"sensitive":false,"dynamic":false},"Transactions Enabled":{"name":"Transactions Enabled","displayName":"Transactions Enabled","identifiesControllerService":false,"sensitive":false,"dynamic":false},"Message Key Field":{"name":"Message Key Field","displayName":"Message Key Field","identifiesControllerService":false,"sensitive":false,"dynamic":false},"FlowFile Attribute Header Pattern":{"name":"FlowFile Attribute Header Pattern","displayName":"FlowFile Attribute Header Pattern","identifiesControllerService":false,"sensitive":false,"dynamic":false}},"style":{},"schedulingPeriod":"0 sec","schedulingStrategy":"TIMER_DRIVEN","executionNode":"ALL","penaltyDuration":"30 sec","yieldDuration":"1 sec","bulletinLevel":"WARN","runDurationMillis":0,"concurrentlySchedulableTaskCount":1,"autoTerminatedRelationships":[],"scheduledState":"ENABLED","retryCount":10,"retriedRelationships":[],"backoffMechanism":"PENALIZE_FLOWFILE","maxBackoffPeriod":"10 mins","componentType":"PROCESSOR","groupIdentifier":"174befb0-0196-1000-15f9-7c703e88cf68"},{"identifier":"d4292f22-44bf-3079-8581-92700b1e2c84","instanceIdentifier":"17781a70-0196-1000-0e9a-0712e06d221b","name":"Log_Invalid_Files","comments":"","position":{"x":-640.0,"y":-64.0},"type":"org.apache.nifi.processors.standard.LogAttribute","bundle":{"group":"org.apache.nifi","artifact":"nifi-standard-nar","version":"2.3.0"},"properties":{"Log prefix":null,"character-set":"UTF-8","Log FlowFile Properties":"true","Log Level":"warn","attributes-to-ignore-regex":null,"Attributes to Ignore":null,"Attributes to Log":"Invalid file ${filename} (empty)","attributes-to-log-regex":".*","Output Format":"Line per Attribute","Log Payload":"false"},"propertyDescriptors":{"Log prefix":{"name":"Log prefix","displayName":"Log prefix","identifiesControllerService":false,"sensitive":false,"dynamic":false},"character-set":{"name":"character-set","displayName":"Character Set","identifiesControllerService":false,"sensitive":false,"dynamic":false},"Log FlowFile Properties":{"name":"Log FlowFile Properties","displayName":"Log FlowFile Properties","identifiesControllerService":false,"sensitive":false,"dynamic":false},"Log Level":{"name":"Log Level","displayName":"Log Level","identifiesControllerService":false,"sensitive":false,"dynamic":false},"attributes-to-ignore-regex":{"name":"attributes-to-ignore-regex","displayName":"Attributes to Ignore by Regular Expression","identifiesControllerService":false,"sensitive":false,"dynamic":false},"Attributes to Ignore":{"name":"Attributes to Ignore","displayName":"Attributes to Ignore","identifiesControllerService":false,"sensitive":false,"dynamic":false},"Attributes to Log":{"name":"Attributes to Log","displayName":"Attributes to Log","identifiesControllerService":false,"sensitive":false,"dynamic":false},"attributes-to-log-regex":{"name":"attributes-to-log-regex","displayName":"Attributes to Log by Regular Expression","identifiesControllerService":false,"sensitive":false,"dynamic":false},"Output Format":{"name":"Output Format","displayName":"Output Format","identifiesControllerService":false,"sensitive":false,"dynamic":false},"Log Payload":{"name":"Log Payload","displayName":"Log Payload","identifiesControllerService":false,"sensitive":false,"dynamic":false}},"style":{},"schedulingPeriod":"0 sec","schedulingStrategy":"TIMER_DRIVEN","executionNode":"ALL","penaltyDuration":"30 sec","yieldDuration":"1 sec","bulletinLevel":"WARN","runDurationMillis":25,"concurrentlySchedulableTaskCount":1,"autoTerminatedRelationships":["success"],"scheduledState":"ENABLED","retryCount":10,"retriedRelationships":[],"backoffMechanism":"PENALIZE_FLOWFILE","maxBackoffPeriod":"10 mins","componentType":"PROCESSOR","groupIdentifier":"174befb0-0196-1000-15f9-7c703e88cf68"},{"identifier":"175457b7-0196-1000-f58a-599b6c9fe07a","instanceIdentifier":"15080729-af9b-3de4-f463-68fb175acddc","name":"Log_JSON_Error","comments":"","position":{"x":696.0,"y":384.0},"type":"org.apache.nifi.processors.standard.LogAttribute","bundle":{"group":"org.apache.nifi","artifact":"nifi-standard-nar","version":"2.3.0"},"properties":{"Log prefix":null,"character-set":"UTF-8","Log FlowFile Properties":"true","Log Level":"error","attributes-to-ignore-regex":null,"Attributes to Ignore":null,"Attributes to Log":"filename, kafka.error","attributes-to-log-regex":".*","Output Format":"Line per Attribute","Log Payload":"false"},"propertyDescriptors":{"Log prefix":{"name":"Log prefix","displayName":"Log prefix","identifiesControllerService":false,"sensitive":false,"dynamic":false},"character-set":{"name":"character-set","displayName":"Character Set","identifiesControllerService":false,"sensitive":false,"dynamic":false},"Log FlowFile Properties":{"name":"Log FlowFile Properties","displayName":"Log FlowFile Properties","identifiesControllerService":false,"sensitive":false,"dynamic":false},"Log Level":{"name":"Log Level","displayName":"Log Level","identifiesControllerService":false,"sensitive":false,"dynamic":false},"attributes-to-ignore-regex":{"name":"attributes-to-ignore-regex","displayName":"Attributes to Ignore by Regular Expression","identifiesControllerService":false,"sensitive":false,"dynamic":false},"Attributes to Ignore":{"name":"Attributes to Ignore","displayName":"Attributes to Ignore","identifiesControllerService":false,"sensitive":false,"dynamic":false},"Attributes to Log":{"name":"Attributes to Log","displayName":"Attributes to Log","identifiesControllerService":false,"sensitive":false,"dynamic":false},"attributes-to-log-regex":{"name":"attributes-to-log-regex","displayName":"Attributes to Log by Regular Expression","identifiesControllerService":false,"sensitive":false,"dynamic":false},"Output Format":{"name":"Output Format","displayName":"Output Format","identifiesControllerService":false,"sensitive":false,"dynamic":false},"Log Payload":{"name":"Log Payload","displayName":"Log Payload","identifiesControllerService":false,"sensitive":false,"dynamic":false}},"style":{},"schedulingPeriod":"0 sec","schedulingStrategy":"TIMER_DRIVEN","executionNode":"ALL","penaltyDuration":"30 sec","yieldDuration":"1 sec","bulletinLevel":"WARN","runDurationMillis":25,"concurrentlySchedulableTaskCount":1,"autoTerminatedRelationships":["success"],"scheduledState":"ENABLED","retryCount":10,"retriedRelationships":[],"backoffMechanism":"PENALIZE_FLOWFILE","maxBackoffPeriod":"10 mins","componentType":"PROCESSOR","groupIdentifier":"174befb0-0196-1000-15f9-7c703e88cf68"},{"identifier":"6ca55f53-9340-3f8f-8342-40fa5565866d","instanceIdentifier":"177a91bf-0196-1000-d82c-4fe2485335f6","name":"Monitor_Pipeline","comments":"","position":{"x":584.0,"y":-464.0},"type":"org.apache.nifi.processors.standard.MonitorActivity","bundle":{"group":"org.apache.nifi","artifact":"nifi-standard-nar","version":"2.3.0"},"properties":{"Continually Send Messages":"false","Inactivity Message":"Lacking activity as of time: ${now():format('yyyy/MM/dd HH:mm:ss')}; flow has been inactive for ${inactivityDurationMillis:toNumber():divide(60000)} minutes","Activity Restored Message":"Activity restored at time: ${now():format('yyyy/MM/dd HH:mm:ss')} after being inactive for ${inactivityDurationMillis:toNumber():divide(60000)} minutes","Copy Attributes":"false","Monitoring Scope":"node","Threshold Duration":"65 min","Wait for Activity":"false","Reset State on Restart":"true","Reporting Node":"all"},"propertyDescriptors":{"Continually Send Messages":{"name":"Continually Send Messages","displayName":"Continually Send Messages","identifiesControllerService":false,"sensitive":false,"dynamic":false},"Inactivity Message":{"name":"Inactivity Message","displayName":"Inactivity Message","identifiesControllerService":false,"sensitive":false,"dynamic":false},"Activity Restored Message":{"name":"Activity Restored Message","displayName":"Activity Restored Message","identifiesControllerService":false,"sensitive":false,"dynamic":false},"Copy Attributes":{"name":"Copy Attributes","displayName":"Copy Attributes","identifiesControllerService":false,"sensitive":false,"dynamic":false},"Monitoring Scope":{"name":"Monitoring Scope","displayName":"Monitoring Scope","identifiesControllerService":false,"sensitive":false,"dynamic":false},"Threshold Duration":{"name":"Threshold Duration","displayName":"Threshold Duration","identifiesControllerService":false,"sensitive":false,"dynamic":false},"Wait for Activity":{"name":"Wait for Activity","displayName":"Wait for Activity","identifiesControllerService":false,"sensitive":false,"dynamic":false},"Reset State on Restart":{"name":"Reset State on Restart","displayName":"Reset State on Restart","identifiesControllerService":false,"sensitive":false,"dynamic":false},"Reporting Node":{"name":"Reporting Node","displayName":"Reporting Node","identifiesControllerService":false,"sensitive":false,"dynamic":false}},"style":{},"schedulingPeriod":"0 sec","schedulingStrategy":"TIMER_DRIVEN","executionNode":"ALL","penaltyDuration":"30 sec","yieldDuration":"1 sec","bulletinLevel":"WARN","runDurationMillis":0,"concurrentlySchedulableTaskCount":1,"autoTerminatedRelationships":["inactive","success","activity.restored"],"scheduledState":"ENABLED","retryCount":10,"retriedRelationships":[],"backoffMechanism":"PENALIZE_FLOWFILE","maxBackoffPeriod":"10 mins","componentType":"PROCESSOR","groupIdentifier":"174befb0-0196-1000-15f9-7c703e88cf68"},{"identifier":"1773722d-0196-1000-cd3e-a19cea8c1085","instanceIdentifier":"e57c4c7c-47c5-3af3-195d-b5d0f3259396","name":"Log_JSON_Success","comments":"","position":{"x":208.0,"y":384.0},"type":"org.apache.nifi.processors.standard.LogAttribute","bundle":{"group":"org.apache.nifi","artifact":"nifi-standard-nar","version":"2.3.0"},"properties":{"Log prefix":null,"character-set":"UTF-8","Log FlowFile Properties":"true","Log Level":"info","attributes-to-ignore-regex":null,"Attributes to Ignore":null,"Attributes to Log":"JSON ${filename} sent to Kafka","attributes-to-log-regex":".*","Output Format":"Line per Attribute","Log Payload":"false"},"propertyDescriptors":{"Log prefix":{"name":"Log prefix","displayName":"Log prefix","identifiesControllerService":false,"sensitive":false,"dynamic":false},"character-set":{"name":"character-set","displayName":"Character Set","identifiesControllerService":false,"sensitive":false,"dynamic":false},"Log FlowFile Properties":{"name":"Log FlowFile Properties","displayName":"Log FlowFile Properties","identifiesControllerService":false,"sensitive":false,"dynamic":false},"Log Level":{"name":"Log Level","displayName":"Log Level","identifiesControllerService":false,"sensitive":false,"dynamic":false},"attributes-to-ignore-regex":{"name":"attributes-to-ignore-regex","displayName":"Attributes to Ignore by Regular Expression","identifiesControllerService":false,"sensitive":false,"dynamic":false},"Attributes to Ignore":{"name":"Attributes to Ignore","displayName":"Attributes to Ignore","identifiesControllerService":false,"sensitive":false,"dynamic":false},"Attributes to Log":{"name":"Attributes to Log","displayName":"Attributes to Log","identifiesControllerService":false,"sensitive":false,"dynamic":false},"attributes-to-log-regex":{"name":"attributes-to-log-regex","displayName":"Attributes to Log by Regular Expression","identifiesControllerService":false,"sensitive":false,"dynamic":false},"Output Format":{"name":"Output Format","displayName":"Output Format","identifiesControllerService":false,"sensitive":false,"dynamic":false},"Log Payload":{"name":"Log Payload","displayName":"Log Payload","identifiesControllerService":false,"sensitive":false,"dynamic":false}},"style":{},"schedulingPeriod":"0 sec","schedulingStrategy":"TIMER_DRIVEN","executionNode":"ALL","penaltyDuration":"30 sec","yieldDuration":"1 sec","bulletinLevel":"WARN","runDurationMillis":25,"concurrentlySchedulableTaskCount":1,"autoTerminatedRelationships":["success"],"scheduledState":"ENABLED","retryCount":10,"retriedRelationships":[],"backoffMechanism":"PENALIZE_FLOWFILE","maxBackoffPeriod":"10 mins","componentType":"PROCESSOR","groupIdentifier":"174befb0-0196-1000-15f9-7c703e88cf68"},{"identifier":"ddba5862-2fdc-3fca-a08a-8f52f8ac8658","instanceIdentifier":"174d9416-0196-1000-c35e-cff908f7801c","name":"Route_by_Type","comments":"","position":{"x":-40.0,"y":-72.0},"type":"org.apache.nifi.processors.standard.RouteOnAttribute","bundle":{"group":"org.apache.nifi","artifact":"nifi-standard-nar","version":"2.3.0"},"properties":{"Routing Strategy":"Route to Property name","csv ":"${filename:endsWith('.csv')}","json":"${filename:endsWith('.json')}"},"propertyDescriptors":{"Routing Strategy":{"name":"Routing Strategy","displayName":"Routing Strategy","identifiesControllerService":false,"sensitive":false,"dynamic":false},"csv ":{"name":"csv ","displayName":"csv ","identifiesControllerService":false,"sensitive":false,"dynamic":true},"json":{"name":"json","displayName":"json","identifiesControllerService":false,"sensitive":false,"dynamic":true}},"style":{},"schedulingPeriod":"0 sec","schedulingStrategy":"TIMER_DRIVEN","executionNode":"ALL","penaltyDuration":"30 sec","yieldDuration":"1 sec","bulletinLevel":"WARN","runDurationMillis":25,"concurrentlySchedulableTaskCount":1,"autoTerminatedRelationships":["unmatched"],"scheduledState":"ENABLED","retryCount":10,"retriedRelationships":[],"backoffMechanism":"PENALIZE_FLOWFILE","maxBackoffPeriod":"10 mins","componentType":"PROCESSOR","groupIdentifier":"174befb0-0196-1000-15f9-7c703e88cf68"},{"identifier":"aeab5e42-60ab-398d-9c65-c629e0da3d99","instanceIdentifier":"1771e6c1-0196-1000-8fea-a20c01f0ed05","name":"Log_CSV_Success","comments":"","position":{"x":-192.0,"y":384.0},"type":"org.apache.nifi.processors.standard.LogAttribute","bundle":{"group":"org.apache.nifi","artifact":"nifi-standard-nar","version":"2.3.0"},"properties":{"Log prefix":null,"character-set":"UTF-8","Log FlowFile Properties":"true","Log Level":"info","attributes-to-ignore-regex":null,"Attributes to Ignore":null,"Attributes to Log":"CSV ${filename} sent to Minio","attributes-to-log-regex":".*","Output Format":"Line per Attribute","Log Payload":"false"},"propertyDescriptors":{"Log prefix":{"name":"Log prefix","displayName":"Log prefix","identifiesControllerService":false,"sensitive":false,"dynamic":false},"character-set":{"name":"character-set","displayName":"Character Set","identifiesControllerService":false,"sensitive":false,"dynamic":false},"Log FlowFile Properties":{"name":"Log FlowFile Properties","displayName":"Log FlowFile Properties","identifiesControllerService":false,"sensitive":false,"dynamic":false},"Log Level":{"name":"Log Level","displayName":"Log Level","identifiesControllerService":false,"sensitive":false,"dynamic":false},"attributes-to-ignore-regex":{"name":"attributes-to-ignore-regex","displayName":"Attributes to Ignore by Regular Expression","identifiesControllerService":false,"sensitive":false,"dynamic":false},"Attributes to Ignore":{"name":"Attributes to Ignore","displayName":"Attributes to Ignore","identifiesControllerService":false,"sensitive":false,"dynamic":false},"Attributes to Log":{"name":"Attributes to Log","displayName":"Attributes to Log","identifiesControllerService":false,"sensitive":false,"dynamic":false},"attributes-to-log-regex":{"name":"attributes-to-log-regex","displayName":"Attributes to Log by Regular Expression","identifiesControllerService":false,"sensitive":false,"dynamic":false},"Output Format":{"name":"Output Format","displayName":"Output Format","identifiesControllerService":false,"sensitive":false,"dynamic":false},"Log Payload":{"name":"Log Payload","displayName":"Log Payload","identifiesControllerService":false,"sensitive":false,"dynamic":false}},"style":{},"schedulingPeriod":"0 sec","schedulingStrategy":"TIMER_DRIVEN","executionNode":"ALL","penaltyDuration":"30 sec","yieldDuration":"1 sec","bulletinLevel":"WARN","runDurationMillis":25,"concurrentlySchedulableTaskCount":1,"autoTerminatedRelationships":["success"],"scheduledState":"ENABLED","retryCount":10,"retriedRelationships":[],"backoffMechanism":"PENALIZE_FLOWFILE","maxBackoffPeriod":"10 mins","componentType":"PROCESSOR","groupIdentifier":"174befb0-0196-1000-15f9-7c703e88cf68"}],"inputPorts":[],"outputPorts":[],"connections":[{"identifier":"9fcee335-7b46-30b7-9768-72b03809b229","instanceIdentifier":"1777d4f6-0196-1000-ea67-67e89d8121e4","name":"","source":{"id":"58fdcc64-3941-3d50-942c-29abd9243e63","type":"PROCESSOR","groupId":"174befb0-0196-1000-15f9-7c703e88cf68","name":"Validate_Files","comments":"","instanceIdentifier":"177671cd-0196-1000-d80c-11354b033e8c"},"destination":{"id":"ddba5862-2fdc-3fca-a08a-8f52f8ac8658","type":"PROCESSOR","groupId":"174befb0-0196-1000-15f9-7c703e88cf68","name":"Route_by_Type","comments":"","instanceIdentifier":"174d9416-0196-1000-c35e-cff908f7801c"},"labelIndex":0,"zIndex":0,"selectedRelationships":["valid"],"backPressureObjectThreshold":10000,"backPressureDataSizeThreshold":"1 GB","flowFileExpiration":"0 sec","prioritizers":[],"bends":[],"loadBalanceStrategy":"DO_NOT_LOAD_BALANCE","partitioningAttribute":"","loadBalanceCompression":"DO_NOT_COMPRESS","componentType":"CONNECTION","groupIdentifier":"174befb0-0196-1000-15f9-7c703e88cf68"},{"identifier":"0dffe210-409d-3672-a5ff-357d5ea64953","instanceIdentifier":"1750510f-0196-1000-9b59-bb5351773067","name":"","source":{"id":"ddba5862-2fdc-3fca-a08a-8f52f8ac8658","type":"PROCESSOR","groupId":"174befb0-0196-1000-15f9-7c703e88cf68","name":"Route_by_Type","comments":"","instanceIdentifier":"174d9416-0196-1000-c35e-cff908f7801c"},"destination":{"id":"174befb6-0196-1000-3f9b-6fd2ea757cb1","type":"PROCESSOR","groupId":"174befb0-0196-1000-15f9-7c703e88cf68","name":"PublishKafka","comments":"","instanceIdentifier":"32ee6041-6780-3c00-59ba-2ecbbe4f32c1"},"labelIndex":0,"zIndex":0,"selectedRelationships":["json"],"backPressureObjectThreshold":10000,"backPressureDataSizeThreshold":"1 GB","flowFileExpiration":"0 sec","prioritizers":[],"bends":[],"loadBalanceStrategy":"DO_NOT_LOAD_BALANCE","partitioningAttribute":"","loadBalanceCompression":"DO_NOT_COMPRESS","componentType":"CONNECTION","groupIdentifier":"174befb0-0196-1000-15f9-7c703e88cf68"},{"identifier":"4bfcf95e-22b2-3a35-8a84-03b7f6a83d53","instanceIdentifier":"17502761-0196-1000-7347-d87131544868","name":"","source":{"id":"ddba5862-2fdc-3fca-a08a-8f52f8ac8658","type":"PROCESSOR","groupId":"174befb0-0196-1000-15f9-7c703e88cf68","name":"Route_by_Type","comments":"","instanceIdentifier":"174d9416-0196-1000-c35e-cff908f7801c"},"destination":{"id":"174befb8-0196-1000-626b-60be34431bf7","type":"PROCESSOR","groupId":"174befb0-0196-1000-15f9-7c703e88cf68","name":"Send_to_Minio","comments":"","instanceIdentifier":"d9755ed1-bb6c-397a-33bc-7c03e3b5cfde"},"labelIndex":0,"zIndex":0,"selectedRelationships":["csv "],"backPressureObjectThreshold":10000,"backPressureDataSizeThreshold":"1 GB","flowFileExpiration":"0 sec","prioritizers":[],"bends":[],"loadBalanceStrategy":"DO_NOT_LOAD_BALANCE","partitioningAttribute":"","loadBalanceCompression":"DO_NOT_COMPRESS","componentType":"CONNECTION","groupIdentifier":"174befb0-0196-1000-15f9-7c703e88cf68"},{"identifier":"2168dbae-875a-3b99-80a7-632d98af2fa5","instanceIdentifier":"1754399d-0196-1000-06d4-1be35d2ba694","name":"","source":{"id":"174befb8-0196-1000-626b-60be34431bf7","type":"PROCESSOR","groupId":"174befb0-0196-1000-15f9-7c703e88cf68","name":"Send_to_Minio","comments":"","instanceIdentifier":"d9755ed1-bb6c-397a-33bc-7c03e3b5cfde"},"destination":{"id":"64a0f0f6-1840-32d3-8e66-09b9409e7fd6","type":"PROCESSOR","groupId":"174befb0-0196-1000-15f9-7c703e88cf68","name":"Log_CSV_Error","comments":"","instanceIdentifier":"1752cce6-0196-1000-e2fd-e74824f2892b"},"labelIndex":0,"zIndex":0,"selectedRelationships":["failure"],"backPressureObjectThreshold":10000,"backPressureDataSizeThreshold":"1 GB","flowFileExpiration":"0 sec","prioritizers":[],"bends":[],"loadBalanceStrategy":"DO_NOT_LOAD_BALANCE","partitioningAttribute":"","loadBalanceCompression":"DO_NOT_COMPRESS","componentType":"CONNECTION","groupIdentifier":"174befb0-0196-1000-15f9-7c703e88cf68"},{"identifier":"c77ea147-89fc-33b1-9db4-f21fe56366c2","instanceIdentifier":"1777b62d-0196-1000-bbe3-ae31179d1730","name":"","source":{"id":"174befb7-0196-1000-5804-f2bc08b4b11e","type":"PROCESSOR","groupId":"174befb0-0196-1000-15f9-7c703e88cf68","name":"Get_All_Files","comments":"","instanceIdentifier":"ff3244f0-3d66-3e11-352c-335a1e91a1cf"},"destination":{"id":"58fdcc64-3941-3d50-942c-29abd9243e63","type":"PROCESSOR","groupId":"174befb0-0196-1000-15f9-7c703e88cf68","name":"Validate_Files","comments":"","instanceIdentifier":"177671cd-0196-1000-d80c-11354b033e8c"},"labelIndex":0,"zIndex":0,"selectedRelationships":["success"],"backPressureObjectThreshold":10000,"backPressureDataSizeThreshold":"1 GB","flowFileExpiration":"0 sec","prioritizers":[],"bends":[],"loadBalanceStrategy":"DO_NOT_LOAD_BALANCE","partitioningAttribute":"","loadBalanceCompression":"DO_NOT_COMPRESS","componentType":"CONNECTION","groupIdentifier":"174befb0-0196-1000-15f9-7c703e88cf68"},{"identifier":"4f6c0e85-aee1-3c1b-addc-df8f9ff786ca","instanceIdentifier":"1778f04c-0196-1000-d32a-0044d346092c","name":"","source":{"id":"58fdcc64-3941-3d50-942c-29abd9243e63","type":"PROCESSOR","groupId":"174befb0-0196-1000-15f9-7c703e88cf68","name":"Validate_Files","comments":"","instanceIdentifier":"177671cd-0196-1000-d80c-11354b033e8c"},"destination":{"id":"d4292f22-44bf-3079-8581-92700b1e2c84","type":"PROCESSOR","groupId":"174befb0-0196-1000-15f9-7c703e88cf68","name":"Log_Invalid_Files","comments":"","instanceIdentifier":"17781a70-0196-1000-0e9a-0712e06d221b"},"labelIndex":0,"zIndex":0,"selectedRelationships":["unmatched"],"backPressureObjectThreshold":10000,"backPressureDataSizeThreshold":"1 GB","flowFileExpiration":"0 sec","prioritizers":[],"bends":[],"loadBalanceStrategy":"DO_NOT_LOAD_BALANCE","partitioningAttribute":"","loadBalanceCompression":"DO_NOT_COMPRESS","componentType":"CONNECTION","groupIdentifier":"174befb0-0196-1000-15f9-7c703e88cf68"},{"identifier":"39d193c8-59ab-3b84-811c-9bfb40912523","instanceIdentifier":"1773a811-0196-1000-057a-358bbfaed68d","name":"","source":{"id":"174befb6-0196-1000-3f9b-6fd2ea757cb1","type":"PROCESSOR","groupId":"174befb0-0196-1000-15f9-7c703e88cf68","name":"PublishKafka","comments":"","instanceIdentifier":"32ee6041-6780-3c00-59ba-2ecbbe4f32c1"},"destination":{"id":"1773722d-0196-1000-cd3e-a19cea8c1085","type":"PROCESSOR","groupId":"174befb0-0196-1000-15f9-7c703e88cf68","name":"Log_JSON_Success","comments":"","instanceIdentifier":"e57c4c7c-47c5-3af3-195d-b5d0f3259396"},"labelIndex":0,"zIndex":0,"selectedRelationships":["success"],"backPressureObjectThreshold":10000,"backPressureDataSizeThreshold":"1 GB","flowFileExpiration":"0 sec","prioritizers":[],"bends":[],"loadBalanceStrategy":"DO_NOT_LOAD_BALANCE","partitioningAttribute":"","loadBalanceCompression":"DO_NOT_COMPRESS","componentType":"CONNECTION","groupIdentifier":"174befb0-0196-1000-15f9-7c703e88cf68"},{"identifier":"ecb5a96e-e27f-3dc5-9352-3c4afeac32fa","instanceIdentifier":"178f0a53-0196-1000-d698-a7a604057c09","name":"","source":{"id":"174befb7-0196-1000-5804-f2bc08b4b11e","type":"PROCESSOR","groupId":"174befb0-0196-1000-15f9-7c703e88cf68","name":"Get_All_Files","comments":"","instanceIdentifier":"ff3244f0-3d66-3e11-352c-335a1e91a1cf"},"destination":{"id":"6ca55f53-9340-3f8f-8342-40fa5565866d","type":"PROCESSOR","groupId":"174befb0-0196-1000-15f9-7c703e88cf68","name":"Monitor_Pipeline","comments":"","instanceIdentifier":"177a91bf-0196-1000-d82c-4fe2485335f6"},"labelIndex":0,"zIndex":0,"selectedRelationships":["success"],"backPressureObjectThreshold":10000,"backPressureDataSizeThreshold":"1 GB","flowFileExpiration":"0 sec","prioritizers":[],"bends":[],"loadBalanceStrategy":"DO_NOT_LOAD_BALANCE","partitioningAttribute":"","loadBalanceCompression":"DO_NOT_COMPRESS","componentType":"CONNECTION","groupIdentifier":"174befb0-0196-1000-15f9-7c703e88cf68"},{"identifier":"a770f068-ed7e-39a9-8b43-ef8c3c250b1a","instanceIdentifier":"1755145d-0196-1000-1e8f-f24e9c3e9204","name":"","source":{"id":"174befb6-0196-1000-3f9b-6fd2ea757cb1","type":"PROCESSOR","groupId":"174befb0-0196-1000-15f9-7c703e88cf68","name":"PublishKafka","comments":"","instanceIdentifier":"32ee6041-6780-3c00-59ba-2ecbbe4f32c1"},"destination":{"id":"175457b7-0196-1000-f58a-599b6c9fe07a","type":"PROCESSOR","groupId":"174befb0-0196-1000-15f9-7c703e88cf68","name":"Log_JSON_Error","comments":"","instanceIdentifier":"15080729-af9b-3de4-f463-68fb175acddc"},"labelIndex":0,"zIndex":0,"selectedRelationships":["failure"],"backPressureObjectThreshold":10000,"backPressureDataSizeThreshold":"1 GB","flowFileExpiration":"0 sec","prioritizers":[],"bends":[],"loadBalanceStrategy":"DO_NOT_LOAD_BALANCE","partitioningAttribute":"","loadBalanceCompression":"DO_NOT_COMPRESS","componentType":"CONNECTION","groupIdentifier":"174befb0-0196-1000-15f9-7c703e88cf68"},{"identifier":"3c1522de-ca33-3119-8ce1-5f410464f7ea","instanceIdentifier":"17725f0e-0196-1000-0b31-f711d7f6c0a5","name":"","source":{"id":"174befb8-0196-1000-626b-60be34431bf7","type":"PROCESSOR","groupId":"174befb0-0196-1000-15f9-7c703e88cf68","name":"Send_to_Minio","comments":"","instanceIdentifier":"d9755ed1-bb6c-397a-33bc-7c03e3b5cfde"},"destination":{"id":"aeab5e42-60ab-398d-9c65-c629e0da3d99","type":"PROCESSOR","groupId":"174befb0-0196-1000-15f9-7c703e88cf68","name":"Log_CSV_Success","comments":"","instanceIdentifier":"1771e6c1-0196-1000-8fea-a20c01f0ed05"},"labelIndex":0,"zIndex":0,"selectedRelationships":["success"],"backPressureObjectThreshold":10000,"backPressureDataSizeThreshold":"1 GB","flowFileExpiration":"0 sec","prioritizers":[],"bends":[],"loadBalanceStrategy":"DO_NOT_LOAD_BALANCE","partitioningAttribute":"","loadBalanceCompression":"DO_NOT_COMPRESS","componentType":"CONNECTION","groupIdentifier":"174befb0-0196-1000-15f9-7c703e88cf68"}],"labels":[],"funnels":[],"controllerServices":[{"identifier":"174befb3-0196-1000-d024-21e680a6371c","instanceIdentifier":"fa6a23b1-6192-3126-b378-3d7817013691","name":"JsonRecordSetWriter","comments":"","type":"org.apache.nifi.json.JsonRecordSetWriter","bundle":{"group":"org.apache.nifi","artifact":"nifi-record-serialization-services-nar","version":"2.3.0"},"properties":{"schema-reference-reader":null,"schema-branch":null,"Allow Scientific Notation":"false","compression-level":"1","schema-cache":null,"Timestamp Format":null,"Date Format":null,"Pretty Print JSON":"false","compression-format":"none","Schema Write Strategy":"no-schema","suppress-nulls":"never-suppress","output-grouping":"output-array","schema-name":"${schema.name}","schema-registry":null,"Time Format":null,"schema-access-strategy":"inherit-record-schema","schema-version":null,"schema-text":"${avro.schema}","Schema Reference Writer":null},"propertyDescriptors":{"schema-reference-reader":{"name":"schema-reference-reader","displayName":"Schema Reference Reader","identifiesControllerService":true,"sensitive":false,"dynamic":false},"schema-branch":{"name":"schema-branch","displayName":"Schema Branch","identifiesControllerService":false,"sensitive":false,"dynamic":false},"Allow Scientific Notation":{"name":"Allow Scientific Notation","displayName":"Allow Scientific Notation","identifiesControllerService":false,"sensitive":false,"dynamic":false},"compression-level":{"name":"compression-level","displayName":"Compression Level","identifiesControllerService":false,"sensitive":false,"dynamic":false},"schema-cache":{"name":"schema-cache","displayName":"Schema Cache","identifiesControllerService":true,"sensitive":false,"dynamic":false},"Timestamp Format":{"name":"Timestamp Format","displayName":"Timestamp Format","identifiesControllerService":false,"sensitive":false,"dynamic":false},"Date Format":{"name":"Date Format","displayName":"Date Format","identifiesControllerService":false,"sensitive":false,"dynamic":false},"Pretty Print JSON":{"name":"Pretty Print JSON","displayName":"Pretty Print JSON","identifiesControllerService":false,"sensitive":false,"dynamic":false},"compression-format":{"name":"compression-format","displayName":"Compression Format","identifiesControllerService":false,"sensitive":false,"dynamic":false},"Schema Write Strategy":{"name":"Schema Write Strategy","displayName":"Schema Write Strategy","identifiesControllerService":false,"sensitive":false,"dynamic":false},"suppress-nulls":{"name":"suppress-nulls","displayName":"Suppress Null Values","identifiesControllerService":false,"sensitive":false,"dynamic":false},"output-grouping":{"name":"output-grouping","displayName":"Output Grouping","identifiesControllerService":false,"sensitive":false,"dynamic":false},"schema-name":{"name":"schema-name","displayName":"Schema Name","identifiesControllerService":false,"sensitive":false,"dynamic":false},"schema-registry":{"name":"schema-registry","displayName":"Schema Registry","identifiesControllerService":true,"sensitive":false,"dynamic":false},"Time Format":{"name":"Time Format","displayName":"Time Format","identifiesControllerService":false,"sensitive":false,"dynamic":false},"schema-access-strategy":{"name":"schema-access-strategy","displayName":"Schema Access Strategy","identifiesControllerService":false,"sensitive":false,"dynamic":false},"schema-version":{"name":"schema-version","displayName":"Schema Version","identifiesControllerService":false,"sensitive":false,"dynamic":false},"schema-text":{"name":"schema-text","displayName":"Schema Text","identifiesControllerService":false,"sensitive":false,"dynamic":false},"Schema Reference Writer":{"name":"Schema Reference Writer","displayName":"Schema Reference Writer","identifiesControllerService":true,"sensitive":false,"dynamic":false}},"controllerServiceApis":[{"type":"org.apache.nifi.serialization.RecordSetWriterFactory","bundle":{"group":"org.apache.nifi","artifact":"nifi-standard-services-api-nar","version":"2.3.0"}}],"scheduledState":"DISABLED","bulletinLevel":"WARN","componentType":"CONTROLLER_SERVICE","groupIdentifier":"174befb0-0196-1000-15f9-7c703e88cf68"},{"identifier":"174befb1-0196-1000-2b5d-6c0654ef430b","instanceIdentifier":"ac791223-cc54-3d18-f2fb-8118623c7b5a","name":"JsonTreeReader","comments":"","type":"org.apache.nifi.json.JsonTreeReader","bundle":{"group":"org.apache.nifi","artifact":"nifi-record-serialization-services-nar","version":"2.3.0"},"properties":{"schema-reference-reader":null,"schema-branch":null,"Max String Length":"20 MB","schema-application-strategy":"SELECTED_PART","Timestamp Format":null,"schema-inference-cache":null,"Date Format":null,"schema-name":"${schema.name}","starting-field-strategy":"ROOT_NODE","schema-registry":null,"starting-field-name":null,"Time Format":null,"schema-access-strategy":"infer-schema","schema-version":null,"schema-text":"${avro.schema}","Allow Comments":"false"},"propertyDescriptors":{"schema-reference-reader":{"name":"schema-reference-reader","displayName":"Schema Reference Reader","identifiesControllerService":true,"sensitive":false,"dynamic":false},"schema-branch":{"name":"schema-branch","displayName":"Schema Branch","identifiesControllerService":false,"sensitive":false,"dynamic":false},"Max String Length":{"name":"Max String Length","displayName":"Max String Length","identifiesControllerService":false,"sensitive":false,"dynamic":false},"schema-application-strategy":{"name":"schema-application-strategy","displayName":"Schema Application Strategy","identifiesControllerService":false,"sensitive":false,"dynamic":false},"Timestamp Format":{"name":"Timestamp Format","displayName":"Timestamp Format","identifiesControllerService":false,"sensitive":false,"dynamic":false},"schema-inference-cache":{"name":"schema-inference-cache","displayName":"Schema Inference Cache","identifiesControllerService":true,"sensitive":false,"dynamic":false},"Date Format":{"name":"Date Format","displayName":"Date Format","identifiesControllerService":false,"sensitive":false,"dynamic":false},"schema-name":{"name":"schema-name","displayName":"Schema Name","identifiesControllerService":false,"sensitive":false,"dynamic":false},"starting-field-strategy":{"name":"starting-field-strategy","displayName":"Starting Field Strategy","identifiesControllerService":false,"sensitive":false,"dynamic":false},"schema-registry":{"name":"schema-registry","displayName":"Schema Registry","identifiesControllerService":true,"sensitive":false,"dynamic":false},"starting-field-name":{"name":"starting-field-name","displayName":"Starting Field Name","identifiesControllerService":false,"sensitive":false,"dynamic":false},"Time Format":{"name":"Time Format","displayName":"Time Format","identifiesControllerService":false,"sensitive":false,"dynamic":false},"schema-access-strategy":{"name":"schema-access-strategy","displayName":"Schema Access Strategy","identifiesControllerService":false,"sensitive":false,"dynamic":false},"schema-version":{"name":"schema-version","displayName":"Schema Version","identifiesControllerService":false,"sensitive":false,"dynamic":false},"schema-text":{"name":"schema-text","displayName":"Schema Text","identifiesControllerService":false,"sensitive":false,"dynamic":false},"Allow Comments":{"name":"Allow Comments","displayName":"Allow Comments","identifiesControllerService":false,"sensitive":false,"dynamic":false}},"controllerServiceApis":[{"type":"org.apache.nifi.serialization.RecordReaderFactory","bundle":{"group":"org.apache.nifi","artifact":"nifi-standard-services-api-nar","version":"2.3.0"}}],"scheduledState":"DISABLED","bulletinLevel":"WARN","componentType":"CONTROLLER_SERVICE","groupIdentifier":"174befb0-0196-1000-15f9-7c703e88cf68"},{"identifier":"174befb2-0196-1000-7005-86a08a1862c1","instanceIdentifier":"43865698-8d80-3dc8-d19d-de97744dcbbc","name":"AWSCredentialsProviderControllerService","comments":"","type":"org.apache.nifi.processors.aws.credentials.provider.service.AWSCredentialsProviderControllerService","bundle":{"group":"org.apache.nifi","artifact":"nifi-aws-nar","version":"2.3.0"},"properties":{"profile-name":null,"assume-role-proxy-configuration-service":null,"default-credentials":"false","Session Time":"3600","assume-role-ssl-context-service":null,"assume-role-sts-signer-override":"Default Signature","custom-signer-class-name":null,"Assume Role ARN":null,"custom-signer-module-location":null,"Assume Role Session Name":null,"assume-role-sts-endpoint":null,"assume-role-sts-region":"us-west-2","Credentials File":null,"assume-role-external-id":null,"anonymous-credentials":"false"},"propertyDescriptors":{"profile-name":{"name":"profile-name","displayName":"Profile Name","identifiesControllerService":false,"sensitive":false,"dynamic":false},"Access Key":{"name":"Access Key","displayName":"Access Key ID","identifiesControllerService":false,"sensitive":true,"dynamic":false},"assume-role-proxy-configuration-service":{"name":"assume-role-proxy-configuration-service","displayName":"Assume Role Proxy Configuration Service","identifiesControllerService":true,"sensitive":false,"dynamic":false},"default-credentials":{"name":"default-credentials","displayName":"Use Default Credentials","identifiesControllerService":false,"sensitive":false,"dynamic":false},"Session Time":{"name":"Session Time","displayName":"Assume Role Session Time","identifiesControllerService":false,"sensitive":false,"dynamic":false},"assume-role-ssl-context-service":{"name":"assume-role-ssl-context-service","displayName":"Assume Role SSL Context Service","identifiesControllerService":true,"sensitive":false,"dynamic":false},"assume-role-sts-signer-override":{"name":"assume-role-sts-signer-override","displayName":"Assume Role STS Signer Override","identifiesControllerService":false,"sensitive":false,"dynamic":false},"custom-signer-class-name":{"name":"custom-signer-class-name","displayName":"Custom Signer Class Name","identifiesControllerService":false,"sensitive":false,"dynamic":false},"Assume Role ARN":{"name":"Assume Role ARN","displayName":"Assume Role ARN","identifiesControllerService":false,"sensitive":false,"dynamic":false},"custom-signer-module-location":{"name":"custom-signer-module-location","displayName":"Custom Signer Module Location","identifiesControllerService":false,"sensitive":false,"dynamic":false,"resourceDefinition":{"cardinality":"MULTIPLE","resourceTypes":["FILE","DIRECTORY"]}},"Assume Role Session Name":{"name":"Assume Role Session Name","displayName":"Assume Role Session Name","identifiesControllerService":false,"sensitive":false,"dynamic":false},"assume-role-sts-endpoint":{"name":"assume-role-sts-endpoint","displayName":"Assume Role STS Endpoint Override","identifiesControllerService":false,"sensitive":false,"dynamic":false},"assume-role-sts-region":{"name":"assume-role-sts-region","displayName":"Assume Role STS Region","identifiesControllerService":false,"sensitive":false,"dynamic":false},"Secret Key":{"name":"Secret Key","displayName":"Secret Access Key","identifiesControllerService":false,"sensitive":true,"dynamic":false},"Credentials File":{"name":"Credentials File","displayName":"Credentials File","identifiesControllerService":false,"sensitive":false,"dynamic":false,"resourceDefinition":{"cardinality":"SINGLE","resourceTypes":["FILE"]}},"assume-role-external-id":{"name":"assume-role-external-id","displayName":"Assume Role External ID","identifiesControllerService":false,"sensitive":false,"dynamic":false},"anonymous-credentials":{"name":"anonymous-credentials","displayName":"Use Anonymous Credentials","identifiesControllerService":false,"sensitive":false,"dynamic":false}},"controllerServiceApis":[{"type":"org.apache.nifi.processors.aws.credentials.provider.service.AWSCredentialsProviderService","bundle":{"group":"org.apache.nifi","artifact":"nifi-aws-service-api-nar","version":"2.3.0"}},{"type":"org.apache.nifi.processors.aws.credentials.provider.AwsCredentialsProviderService","bundle":{"group":"org.apache.nifi","artifact":"nifi-aws-service-api-nar","version":"2.3.0"}}],"scheduledState":"DISABLED","bulletinLevel":"WARN","componentType":"CONTROLLER_SERVICE","groupIdentifier":"174befb0-0196-1000-15f9-7c703e88cf68"},{"identifier":"174befb4-0196-1000-0bc1-7163d0c50f3f","instanceIdentifier":"5adc3989-ed49-3e56-2712-f2eca4777046","name":"Kafka3ConnectionService","comments":"","type":"org.apache.nifi.kafka.service.Kafka3ConnectionService","bundle":{"group":"org.apache.nifi","artifact":"nifi-kafka-3-service-nar","version":"2.3.0"},"properties":{"security.protocol":"PLAINTEXT","SSL Context Service":null,"ack.wait.time":"5 sec","sasl.username":null,"max.poll.records":"10000","sasl.mechanism":"GSSAPI","isolation.level":"read_committed","max.block.ms":"5 sec","bootstrap.servers":"kafka:9092","kerberos-user-service":null,"sasl.kerberos.service.name":null,"default.api.timeout.ms":"60 sec"},"propertyDescriptors":{"ack.wait.time":{"name":"ack.wait.time","displayName":"Acknowledgment Wait Time","identifiesControllerService":false,"sensitive":false,"dynamic":false},"sasl.username":{"name":"sasl.username","displayName":"SASL Username","identifiesControllerService":false,"sensitive":false,"dynamic":false},"max.poll.records":{"name":"max.poll.records","displayName":"Max Poll Records","identifiesControllerService":false,"sensitive":false,"dynamic":false},"bootstrap.servers":{"name":"bootstrap.servers","displayName":"Bootstrap Servers","identifiesControllerService":false,"sensitive":false,"dynamic":false},"sasl.kerberos.service.name":{"name":"sasl.kerberos.service.name","displayName":"Kerberos Service Name","identifiesControllerService":false,"sensitive":false,"dynamic":false},"security.protocol":{"name":"security.protocol","displayName":"Security Protocol","identifiesControllerService":false,"sensitive":false,"dynamic":false},"SSL Context Service":{"name":"SSL Context Service","displayName":"SSL Context Service","identifiesControllerService":true,"sensitive":false,"dynamic":false},"sasl.mechanism":{"name":"sasl.mechanism","displayName":"SASL Mechanism","identifiesControllerService":false,"sensitive":false,"dynamic":false},"isolation.level":{"name":"isolation.level","displayName":"Transaction Isolation Level","identifiesControllerService":false,"sensitive":false,"dynamic":false},"max.block.ms":{"name":"max.block.ms","displayName":"Max Metadata Wait Time","identifiesControllerService":false,"sensitive":false,"dynamic":false},"kerberos-user-service":{"name":"kerberos-user-service","displayName":"Kerberos User Service","identifiesControllerService":true,"sensitive":false,"dynamic":false},"sasl.password":{"name":"sasl.password","displayName":"SASL Password","identifiesControllerService":false,"sensitive":true,"dynamic":false},"default.api.timeout.ms":{"name":"default.api.timeout.ms","displayName":"Client Timeout","identifiesControllerService":false,"sensitive":false,"dynamic":false}},"controllerServiceApis":[{"type":"org.apache.nifi.kafka.service.api.KafkaConnectionService","bundle":{"group":"org.apache.nifi","artifact":"nifi-kafka-service-api-nar","version":"2.3.0"}}],"scheduledState":"DISABLED","bulletinLevel":"WARN","componentType":"CONTROLLER_SERVICE","groupIdentifier":"174befb0-0196-1000-15f9-7c703e88cf68"}],"defaultFlowFileExpiration":"0 sec","defaultBackPressureObjectThreshold":10000,"defaultBackPressureDataSizeThreshold":"1 GB","scheduledState":"ENABLED","executionEngine":"INHERITED","maxConcurrentTasks":1,"statelessFlowTimeout":"1 min","flowFileConcurrency":"UNBOUNDED","flowFileOutboundPolicy":"STREAM_WHEN_AVAILABLE","componentType":"PROCESS_GROUP"},"externalControllerServices":{},"parameterContexts":{},"flowEncodingVersion":"1.0","parameterProviders":{},"latest":false}